plasan/__init__.py
plasan/annotate_plasmid.py
plasan/draw_plasmid.py
plasan/essential_annotation.py
plasan/main.py
plasan-0.1.dist-info/METADATA
plasan-0.1.dist-info/WHEEL
plasan-0.1.dist-info/entry_points.txt
plasan-0.1.dist-info/top_level.txt
plasan-0.1.dist-info/RECORD
